easycache/__init__.py
easycache/easycache.py
easycache/json_encoder.py
rosetta_easycache-0.1.2.dist-info/METADATA
rosetta_easycache-0.1.2.dist-info/WHEEL
rosetta_easycache-0.1.2.dist-info/top_level.txt
rosetta_easycache-0.1.2.dist-info/RECORD
