Metadata-Version: 2.1
Name: rosetta-easycache
Version: 0.1.2
Summary: 一个快速使用异步redis优化数据库查询项目
Home-page: https://git.duowan.com/ai/nlp/easy-cache
Author: Zhiyuan Zhang
Author-email: zhangzhiyuan1@joyy.com
License: UNKNOWN
Platform: UNKNOWN
Classifier: Programming Language :: Python :: 3
Classifier: License :: OSI Approved :: MIT License
Classifier: Operating System :: OS Independent
Requires-Python: >=3.7
Requires-Dist: ujson
Requires-Dist: loguru
